tests/urbanopt_ditto_reader/test_ditto_reader_cli.py
urbanopt_ditto_reader/__init__.py
urbanopt_ditto_reader/ditto_reader_cli.py
urbanopt_ditto_reader/example_config.json
urbanopt_ditto_reader/extended_catalog.json
urbanopt_ditto_reader/urbanopt_ditto_reader.py
urbanopt_ditto_reader/reader/__init__.py
urbanopt_ditto_reader/reader/read.py
urbanopt_ditto_reader-0.6.4.dist-info/LICENSE.md
urbanopt_ditto_reader-0.6.4.dist-info/METADATA
urbanopt_ditto_reader-0.6.4.dist-info/WHEEL
urbanopt_ditto_reader-0.6.4.dist-info/entry_points.txt
urbanopt_ditto_reader-0.6.4.dist-info/top_level.txt
urbanopt_ditto_reader-0.6.4.dist-info/RECORD
