Metadata-Version: 2.1
Name: urbanopt-ditto-reader
Version: 0.6.4
Summary: Enhancement of URBANopt GeoJSON that can be consumed by DiTTo reader
Author-email: Tarek Elgindy <tarek.elgindy@nrel.gov>, Nathan Moore <nathan.moore@nrel.gov>, Katherine Fleming <katherine.fleming@nrel.gov>
Project-URL: Homepage, https://github.com/urbanopt/urbanopt-ditto-reader
Project-URL: Bug Tracker, https://github.com/urbanopt/urbanopt-ditto-reader/issues
Classifier: Development Status :: 4 - Beta
Classifier: Environment :: Console
Classifier: Intended Audience :: Developers
Classifier: Intended Audience :: Science/Research
Classifier: Topic :: Scientific/Engineering
Classifier: Operating System :: OS Independent
Classifier: Programming Language :: Python :: 3.8
Classifier: Programming Language :: Python :: 3.9
Classifier: Programming Language :: Python :: 3.10
Classifier: Programming Language :: Python :: 3.11
Classifier: Programming Language :: Python :: 3.12
Requires-Python: ~=3.8
License-File: LICENSE.md
Requires-Dist: ditto.py[opendss] ~=0.2.4
Requires-Dist: opendssdirect.py ~=0.8.0
Provides-Extra: dev
Requires-Dist: pytest ~=7.4 ; extra == 'dev'
Requires-Dist: pre-commit ~=3.3 ; extra == 'dev'
Requires-Dist: ruff ~=0.4.0 ; extra == 'dev'
